revauth/__init__.py
revauth/config.py
revauth/exceptions.py
revauth/handlers.py
revauth/jwt.py
revauth/models.py
revauth/notifications.py
revauth/serializers.py
revauth/settings.py
revauth/urls.py
revauth/views.py
revauth/migrations/0001_initial.py
revauth/migrations/__init__.py
revauth/socials/__init__.py
revauth/socials/providers.py
revauth/socials/social_signin.py
revauth/utils/__init__.py
revauth-1.0.7.dist-info/METADATA
revauth-1.0.7.dist-info/WHEEL
revauth-1.0.7.dist-info/top_level.txt
revauth-1.0.7.dist-info/RECORD
