Metadata-Version: 2.1
Name: revauth
Version: 1.0.7
Summary: auth service for revteltech
Home-page: https://github.com/revtel/revauth
Author: Chien Hsiao
Author-email: chien.hsiao@revteltech.com
License: MIT
Keywords: revteltech,auth
Platform: UNKNOWN
Classifier: Development Status :: 3 - Alpha
Classifier: Intended Audience :: Developers
Classifier: Topic :: Software Development :: Build Tools
Classifier: License :: OSI Approved :: MIT License
Classifier: Programming Language :: Python :: 3
Classifier: Programming Language :: Python :: 3.6
Classifier: Programming Language :: Python :: 3.7
Requires-Dist: django
Requires-Dist: djangorestframework
Requires-Dist: requests
Requires-Dist: revjwt
Requires-Dist: revns
